astar_devopstool/__init__.py
astar_devopstool/common.py
astar_devopstool/connect.py
astar_devopstool/emailtool.py
astar_devopstool/exception.py
astar_devopstool/host.py
astar_devopstool/ip.py
astar_devopstool/dev/__init__.py
astar_devopstool/dev/_develop.py
astar_devopstool/ftphelper/__init__.py
astar_devopstool/ftphelper/_ftphelper.py
astar_devopstool/gitlabhelper/__init__.py
astar_devopstool/gitlabhelper/_gitlabhelper.py
astar_devopstool/test/__init__.py
astar_devopstool/test/test_version.py
astar_devopstool/version_announcement/__init__.py
astar_devopstool/version_announcement/_report.py
astar_devopstool/version_announcement/_version.py
astar_devopstool-0.0.7.dist-info/LICENSE
astar_devopstool-0.0.7.dist-info/METADATA
astar_devopstool-0.0.7.dist-info/WHEEL
astar_devopstool-0.0.7.dist-info/top_level.txt
astar_devopstool-0.0.7.dist-info/RECORD
