Metadata-Version: 2.1
Name: astar-devopstool
Version: 0.0.7
Summary: Python devopstool
Home-page: https://github.com/astar-club/astar-devopstool-python
Author: A.Star
Author-email: astar@snowland.ltd
Maintainer: A.Star
Maintainer-email: astar@snowland.ltd
License: Apache v2.0 License
Platform: all
Classifier: Operating System :: OS Independent
Classifier: Intended Audience :: Developers
Classifier: License :: OSI Approved :: BSD License
Classifier: Programming Language :: Python
Classifier: Programming Language :: Python :: Implementation
Classifier: Programming Language :: Python :: 2
Classifier: Programming Language :: Python :: 2.7
Classifier: Programming Language :: Python :: 3
Classifier: Programming Language :: Python :: 3.6
Classifier: Programming Language :: Python :: 3.7
Classifier: Programming Language :: Python :: 3.8
Classifier: Programming Language :: Python :: 3.9
Classifier: Programming Language :: Python :: 3.10
Classifier: Topic :: Software Development :: Libraries
License-File: LICENSE
Requires-Dist: paramiko (>=2.4.2)
Requires-Dist: astartool (>=0.0.9)
Requires-Dist: psutil
Requires-Dist: python-gitlab (>=2.0.0)
Requires-Dist: GPUtil
